image_image/__init__.py
image_image/processing/__init__.py
image_image/processing/combination.py
image_image/processing/transformation.py
image_image/utils/__init__.py
image_image/utils/io.py
image_image/utils/plot.py
image_processing/__init__.py
image_processing/processing/__init__.py
image_processing/processing/combination.py
image_processing/processing/transformation.py
image_processing/utils/__init__.py
image_processing/utils/io.py
image_processing/utils/plot.py
image_processing323/__init__.py
image_processing323/processing/__init__.py
image_processing323/processing/combination.py
image_processing323/processing/transformation.py
image_processing323/utils/__init__.py
image_processing323/utils/io.py
image_processing323/utils/plot.py
image_image-0.0.1.dist-info/METADATA
image_image-0.0.1.dist-info/WHEEL
image_image-0.0.1.dist-info/top_level.txt
image_image-0.0.1.dist-info/RECORD
