Metadata-Version: 2.1
Name: image-image
Version: 0.0.1
Summary: pacote de processamento de imagem teste
Home-page: UNKNOWN
Author: Leonardo Alves de Andrade
Author-email: leonardo.andrade@engenharia.ufjf.br
License: UNKNOWN
Platform: UNKNOWN
Requires-Python: >=3.0
